drivers/__init__.py
drivers/common_actions.py
drivers/web_browser.py
integrations/__init__.py
integrations/get_library.py
reports/__init__.py
softassert/__init__.py
softassert/assertion.py
softassert/pytest_softassert.py
tests/__init__.py
tests/test_file_helper.py
tests/test_helper.py
tests/test_json_utils.py
tests/test_mark_demo.py
tests/test_screenshot_helper.py
tests/test_settings_loader.py
tests/test_soft_assertion.py
tests/test_web_browser.py
utils/__init__.py
utils/email.py
utils/file_helper.py
utils/helper.py
utils/json_utils.py
utils/screenshot_helper.py
utils/settings_loader.py
test_soft_assertion_tool-0.2.0.dist-info/METADATA
test_soft_assertion_tool-0.2.0.dist-info/WHEEL
test_soft_assertion_tool-0.2.0.dist-info/entry_points.txt
test_soft_assertion_tool-0.2.0.dist-info/top_level.txt
test_soft_assertion_tool-0.2.0.dist-info/RECORD
